nsefin/__init__.py
nsefin/api.py
nsefin/models.py
nsefin-0.1.5.dist-info/LICENSE
nsefin-0.1.5.dist-info/METADATA
nsefin-0.1.5.dist-info/WHEEL
nsefin-0.1.5.dist-info/top_level.txt
nsefin-0.1.5.dist-info/RECORD
