Metadata-Version: 2.1
Name: nsefin
Version: 0.1.5
Summary: A Python library to download publicly available historical candlestick data from NSE India
Home-page: https://github.com/vbhadala/nsefin
Author: Vinod Bhadala
Author-email: vinodbhadala@gmail.com
Keywords: nse,stock market,financial data,india,trading,candlestick data
Classifier: Development Status :: 3 - Alpha
Classifier: Intended Audience :: Financial and Insurance Industry
Classifier: License :: OSI Approved :: MIT License
Classifier: Operating System :: OS Independent
Classifier: Programming Language :: Python :: 3
Classifier: Programming Language :: Python :: 3.8
Classifier: Programming Language :: Python :: 3.9
Classifier: Programming Language :: Python :: 3.10
Classifier: Programming Language :: Python :: 3.11
Classifier: Topic :: Office/Business :: Financial :: Investment
Requires-Python: >=3.9
License-File: LICENSE
Requires-Dist: pandas>=2.0.0
Requires-Dist: requests>=2.25.0
Requires-Dist: pydantic>=2.0.0
Requires-Dist: volg>=0.1.5
